Metadata-Version: 2.1
Name: python-libmilter
Version: 2.0.0
Summary: A pure python implementation of libmilter
Home-page: http://stuffivelearned.org/doku.php?id=programming:python:python-libmilter
Author: Jay Deiman
Author-email: admin@splitstreams.com
License: UNKNOWN
Platform: UNKNOWN
Classifier: Development Status :: 4 - Beta
Classifier: Environment :: No Input/Output (Daemon)
Classifier: Intended Audience :: System Administrators
Classifier: Intended Audience :: Information Technology
Classifier: License :: OSI Approved :: GNU General Public License (GPL)
Classifier: Natural Language :: English
Classifier: Operating System :: POSIX
Classifier: Programming Language :: Python
Classifier: Topic :: System :: Systems Administration
Classifier: Topic :: System
License-File: LICENSE
